falcon_rethinkdb/__init__.py
falcon_rethinkdb/hooks.py
falcon_rethinkdb/resource.py
falcon_rethinkdb/types.py
falcon_rethinkdb/util.py
falcon_rethinkdb-0.2.2.dist-info/DESCRIPTION.rst
falcon_rethinkdb-0.2.2.dist-info/METADATA
falcon_rethinkdb-0.2.2.dist-info/RECORD
falcon_rethinkdb-0.2.2.dist-info/WHEEL
falcon_rethinkdb-0.2.2.dist-info/metadata.json
falcon_rethinkdb-0.2.2.dist-info/top_level.txt
