Metadata-Version: 2.0
Name: falcon-rethinkdb
Version: 0.2.2
Summary: Falcon extension to easily use RethinkDB
Home-page: https://github.com/vixcess/falcon-rethinkdb
Author: Shiqiao Du
Author-email: lucidfrontier.45@gmail.com
License: Apache License version 2
Platform: UNKNOWN
Classifier: Programming Language :: Python :: 3.4
Classifier: Programming Language :: Python :: 3.5
Requires-Dist: falcon
Requires-Dist: rethinkdb
Requires-Dist: jsonschema
Requires-Dist: toolz
